openexchangerates/__init__.py
openexchangerates/tests.py
openexchangerates-0.1.0.dist-info/DESCRIPTION.rst
openexchangerates-0.1.0.dist-info/METADATA
openexchangerates-0.1.0.dist-info/pydist.json
openexchangerates-0.1.0.dist-info/RECORD
openexchangerates-0.1.0.dist-info/top_level.txt
openexchangerates-0.1.0.dist-info/WHEEL
