Metadata-Version: 2.0
Name: openexchangerates
Version: 0.1.0
Summary: openexchangerates.org python API client
Home-page: https://github.com/metglobal/openexchangerates
Author: Metglobal
Author-email: kadir.pekel@metglobal.com
License: MIT
Platform: UNKNOWN
Classifier: Development Status :: 5 - Production/Stable
Classifier: Intended Audience :: Developers
Classifier: Natural Language :: English
Classifier: License :: OSI Approved :: MIT License
Classifier: Operating System :: OS Independent
Classifier: Programming Language :: Python
Classifier: Programming Language :: Python :: 2.7
Classifier: Topic :: Internet :: WWW/HTTP
Requires-Dist: requests
